lavavu/lavavu.py
lavavu/vutils.py
lavavu/dict.json
lavavu/server.py
lavavu/points.py
lavavu/_LavaVuPython.cpython-312-darwin.so
lavavu/LavaVuPython.py
lavavu/tracers.py
lavavu/convert.py
lavavu/control.py
lavavu/__init__.py
lavavu/amalgamate.py
lavavu/aserver.py
lavavu/font.bin
lavavu/__main__.py
lavavu/html/control.css
lavavu/html/control.js
lavavu/html/gui.css
lavavu/html/favicon.ico
lavavu/html/LavaVu-amalgamated.css
lavavu/html/styles.css
lavavu/html/gl-matrix-min.js
lavavu/html/webview-template.html
lavavu/html/stats.min.js
lavavu/html/server.js
lavavu/html/dat.gui.min.js
lavavu/html/OK-min.js
lavavu/html/emscripten.css
lavavu/html/drawbox.js
lavavu/html/webview.html
lavavu/html/emscripten-template.js
lavavu/html/draw.js
lavavu/html/dat-gui-light-theme.css
lavavu/html/menu.js
lavavu/html/baseviewer.js
lavavu/osmesa/LavaVuPython.py
lavavu/osmesa/__init__.py
lavavu/shaders/volumeShader.frag
lavavu/shaders/pointShader.vert
lavavu/shaders/lineShader.frag
lavavu/shaders/fontShader.frag
lavavu/shaders/triShader.frag
lavavu/shaders/default.vert
lavavu/shaders/triShader.vert
lavavu/shaders/lineShader.vert
lavavu/shaders/fontShader.vert
lavavu/shaders/pointShader.frag
lavavu/shaders/volumeShader.vert
lavavu/shaders/default.frag
lavavu-1.9.9.dist-info/RECORD
lavavu-1.9.9.dist-info/WHEEL
lavavu-1.9.9.dist-info/entry_points.txt
lavavu-1.9.9.dist-info/top_level.txt
lavavu-1.9.9.dist-info/METADATA
lavavu-1.9.9.dist-info/licenses/LICENSE.md
